entmoot/__init__.py
entmoot/__version__.py
entmoot/benchmarks.py
entmoot/constraints.py
entmoot/problem_config.py
entmoot/utils.py
entmoot/models/__init__.py
entmoot/models/base_model.py
entmoot/models/enting.py
entmoot/models/model_params.py
entmoot/models/mean_models/__init__.py
entmoot/models/mean_models/lgbm_utils.py
entmoot/models/mean_models/meta_tree_ensemble.py
entmoot/models/mean_models/tree_ensemble.py
entmoot/models/uncertainty_models/__init__.py
entmoot/models/uncertainty_models/base_distance.py
entmoot/models/uncertainty_models/distance_based_uncertainty.py
entmoot/models/uncertainty_models/euclidean_squared_distance.py
entmoot/models/uncertainty_models/goodall4_distance.py
entmoot/models/uncertainty_models/l1_distance.py
entmoot/models/uncertainty_models/l2_distance.py
entmoot/models/uncertainty_models/of_distance.py
entmoot/models/uncertainty_models/overlap_distance.py
entmoot/optimizers/__init__.py
entmoot/optimizers/base_opt.py
entmoot/optimizers/gurobi_opt.py
entmoot/optimizers/pyomo_opt.py
entmoot/optimizers/sampling_opt.py
entmoot/typing/__init__.py
entmoot/typing/optimizer_stubs.py
entmoot-2.0.6.dist-info/LICENSE
entmoot-2.0.6.dist-info/METADATA
entmoot-2.0.6.dist-info/WHEEL
entmoot-2.0.6.dist-info/top_level.txt
entmoot-2.0.6.dist-info/RECORD
